twcompose/__init__.py
twcompose/__main__.py
twcompose/cli.py
twcompose/compose.py
twcompose/rules.py
twcompose/utils.py
twcompose/backends/__init__.py
twcompose/backends/abstract.py
twcompose/backends/docker.py
twcompose/commands/__init__.py
twcompose/commands/config.py
twcompose/commands/status.py
twcompose/commands/stop.py
twcompose/commands/update.py
twcompose/commands/volume.py
twcompose/handlers/__init__.py
twcompose/handlers/base.py
twcompose/handlers/config.py
twcompose/handlers/messages.py
twcompose/handlers/state.py
twcompose/handlers/twitter.py
twcompose/handlers/volume.py
twcompose/twitter/__init__.py
twcompose/twitter/client.py
twcompose/twitter/counts.py
twcompose-0.1.0.dist-info/LICENSE.txt
twcompose-0.1.0.dist-info/METADATA
twcompose-0.1.0.dist-info/WHEEL
twcompose-0.1.0.dist-info/entry_points.txt
twcompose-0.1.0.dist-info/top_level.txt
twcompose-0.1.0.dist-info/RECORD
