Metadata-Version: 2.1
Name: twcompose
Version: 0.1.0
Summary: CLI to manage rules and start tweets collection from the Twitter Stream API
Home-page: https://github.com/smassonnet/twcompose
Author: Stephane Massonnet
Author-email: stephane.massonnet@epfl.ch
License: MIT
Project-URL: Documentation, https://github.com/smassonnet/twcompose
Project-URL: Source, https://github.com/smassonnet/twcompose
Project-URL: Changelog, https://github.com/smassonnet/twcompose/releases
Project-URL: Tracker, https://github.com/smassonnet/twcompose/issues
Project-URL: Download, https://pypi.org/project/twcompose/#files
Platform: any
Classifier: Development Status :: 4 - Beta
Classifier: Programming Language :: Python
Requires-Python: >=3.8
License-File: LICENSE.txt
Requires-Dist: docker
Requires-Dist: twcollect (>=0.1.0)
Requires-Dist: tweepy
Provides-Extra: testing
Requires-Dist: setuptools ; extra == 'testing'
Requires-Dist: pytest ; extra == 'testing'
Requires-Dist: pytest-cov ; extra == 'testing'
